setup.py
efpy/__init__.py
efpy/env.py
efpy/expHelper.py
efpy/templates.py
efpy.egg-info/PKG-INFO
efpy.egg-info/SOURCES.txt
efpy.egg-info/dependency_links.txt
efpy.egg-info/requires.txt
efpy.egg-info/top_level.txt