Metadata-Version: 2.1
Name: efpy
Version: 0.1.16
Summary: experience
Home-page: https://github.com/imcjp/efpy
Author: Cai Jianping
Author-email: jpingcai@163.com
License: MIT Licence
Keywords: experience,environment
Platform: any
Requires-Dist: PyYAML
